phylopandas/__init__.py
phylopandas/__version__.py
phylopandas/core.py
phylopandas/dataframe.py
phylopandas/frame.py
phylopandas/phylopandas.py
phylopandas/read.py
phylopandas/utils.py
phylopandas/write.py
phylopandas/msa_new/__init__.py
phylopandas/msa_new/color_schemes.py
phylopandas/seqio/__init__.py
phylopandas/seqio/read.py
phylopandas/seqio/write.py
phylopandas/tests/__init__.py
phylopandas/tests/test_dataframe.py
phylopandas/tests/test_frame.py
phylopandas/tests/test_phylopandas.py
phylopandas/tests/test_series.py
phylopandas/treeio/__init__.py
phylopandas/treeio/mixin.py
phylopandas/treeio/read.py
phylopandas/treeio/write.py
phylopandas/treeio/tests/__init__.py
phylopandas/treeio/tests/test_read.py
phylopandas/viz/__init__.py
phylopandas-0.8.0.dist-info/LICENSE
phylopandas-0.8.0.dist-info/METADATA
phylopandas-0.8.0.dist-info/WHEEL
phylopandas-0.8.0.dist-info/top_level.txt
phylopandas-0.8.0.dist-info/RECORD
