Metadata-Version: 2.1
Name: phylopandas
Version: 0.8.0
Summary: Pandas for phylogenetics
Home-page: https://github.com/Zsailer/phylopandas
Author: Zachary Sailer
Author-email: zachsailer@gmail.com
License: MIT
Platform: UNKNOWN
Classifier: License :: OSI Approved :: MIT License
Classifier: Programming Language :: Python
Classifier: Programming Language :: Python :: 3
Classifier: Programming Language :: Python :: 3.6
Classifier: Programming Language :: Python :: Implementation :: CPython
Classifier: Programming Language :: Python :: Implementation :: PyPy
Requires-Python: >=3.0
Requires-Dist: pandas (>=0.22.0)
Requires-Dist: pandas-flavor (>=0.1.0)
Requires-Dist: biopython
Requires-Dist: dendropy
